{ "folder_name" : "Model_D2_sensitivity_analysis",
  "modelID" : "HBS",
  "topologies" : ["simple", "H1a_fb", "H2a_fb"],
  "dataID" : "hypoxia_only",
  "mechanismID" : "D2",
  "context" : "/Users/kdreyer/Documents/Github/HBS_GAMES2/src/games/",
  "parameters" : [58.84038294, 19.394864946748044, 1.2054401450995096, 8.258735426, 0.1943380032233462, 0.08933521, 0.029685513135329716, 0.5866584094797468, 0.4750821811283993, 8.224385115381692], 
  "parameters_reference" : [],
  "parameter_labels" : ["t_HAF", "k_txn2", "k_dHAF", "k_bHS", "k_bHH", "k_txnH", "k_dH1R", "k_dH1P", "k_dHP", "k_txnBH"],
  "free_parameter_labels" : ["t_HAF", "k_txn2", "k_dHAF", "k_bHS", "k_bHH", "k_txnH", "k_dH1R", "k_dH1P", "k_dHP", "k_txnBH"],
  "bounds_orders_of_magnitude" : 3,
  "non_default_bounds": {"t_HAF" : [1.3802, 1.8573]},
  "num_parameter_sets_global_search" : 1000, 
  "num_parameter_sets_optimization" : 100,
  "weight_by_error" : "no",
  "num_pem_evaluation_datasets" : 3, 
  "parallelization" : "yes", 
  "num_cores" : 8
}



